Metadata-Version: 1.1
Name: uwosh.timeslot
Version: 1.5.6
Summary: A Plone scheduling product that lets you make easy signup sheets for office hours and class registrations
Home-page: http://www.uwosh.edu/ploneprojects/
Author: Marshall Scorcio
Author-email: marshall.scorcio@gmail.com
License: GPL
Platform: UNKNOWN
Classifier: Framework :: Plone
Classifier: Intended Audience :: Developers
Classifier: Topic :: Software Development :: Libraries :: Python Modules
Classifier: License :: OSI Approved :: GNU General Public License (GPL)
